<ns0:demographics xmlns:ns0="http://www.zillow.com/static/xsd/Demographics.xsd" xmlns:xsi="http://www.w3.org/2001/XMLSchema-instance" xsi:schemaLocation="http://www.zillow.com/static/xsd/Demographics.xsd http://www.zillowstatic.com/vstatic/f7a2366/static/xsd/Demographics.xsd"><request><state>IL</state><city>chicago</city><neighborhood>Oakland</neighborhood></request><message><text>Request successfully processed</text><code>0</code></message><response><region><id>274850</id><state>Illinois</state><city>Chicago</city><neighborhood>Oakland</neighborhood><latitude>41.824073</latitude><longitude>-87.601449</longitude><zmmrateurl>http://www.zillow.com/mortgage-rates/il/chicago/</zmmrateurl></region><links><main>http://www.zillow.com/oakland-chicago-il/</main><affordability>http://www.zillow.com/local-info/IL-Chicago/Oakland-home-value/r_274850/</affordability><homesandrealestate>http://www.zillow.com/local-info/IL-Chicago/Oakland-homes/r_274850/</homesandrealestate><people>http://www.zillow.com/local-info/IL-Chicago/Oakland-people/r_274850/</people><forSale>http://www.zillow.com/oakland-chicago-il/</forSale><forSaleByOwner>http://www.zillow.com/oakland-chicago-il/fsbo/</forSaleByOwner><foreclosures>http://www.zillow.com/oakland-chicago-il/fore_lt/pmf_pt/</foreclosures><recentlySold>http://www.zillow.com/oakland-chicago-il/sold/</recentlySold></links><charts><chart><name>Median Condo Value</name><url>http://www.zillow.com/app?chartType=affordability_avgCondoValue&amp;graphType=barChart&amp;regionId=274850&amp;regionType=8&amp;service=chart</url></chart><chart><name>Median Home Value</name><url>http://www.zillow.com/app?chartType=affordability_avgHomeValue&amp;graphType=barChart&amp;regionId=274850&amp;regionType=8&amp;service=chart</url></chart><chart><name>Dollars Per Square Feet</name><url>http://www.zillow.com/app?chartType=affordability_pricePerSqft&amp;graphType=barChart&amp;regionId=274850&amp;regionType=8&amp;service=chart</url></chart><chart><name deprecated="true">Zillow Home Value Index Distribution</name><url>http://www.zillow.com/app?chartType=affordability_ZindexByDistribution&amp;graphType=barChart&amp;regionId=274850&amp;regionType=8&amp;service=chart</url></chart><chart><name>Home Type</name><url>http://www.zillow.com/app?chartType=home_homeType&amp;graphType=barChart&amp;regionId=274850&amp;regionType=8&amp;service=chart</url></chart><chart><name deprecated="true">Owners vs. Renters</name><url>http://www.zillow.com/app?chartType=home_ownVsRent&amp;graphType=barChart&amp;regionId=274850&amp;regionType=8&amp;service=chart</url></chart><chart><name>Home Size in Square Feet</name><url>http://www.zillow.com/app?chartType=home_homeSize&amp;graphType=barChart&amp;regionId=274850&amp;regionType=8&amp;service=chart</url></chart><chart><name>Year Built</name><url>http://www.zillow.com/app?chartType=home_yearBuilt&amp;graphType=barChart&amp;regionId=274850&amp;regionType=8&amp;service=chart</url></chart></charts><market deprecated="true" /><pages><page><name>Affordability</name><tables><table><name>Affordability Data</name><data><attribute><name>Zillow Home Value Index</name><values><neighborhood><value type="USD">268800</value></neighborhood><city><value type="USD">191500</value></city><nation><value type="USD">180100</value></nation></values></attribute><attribute><name>Median Single Family Home Value</name><values><neighborhood><value type="USD">327700</value></neighborhood><city><value type="USD">172700</value></city><nation><value type="USD">179700</value></nation></values></attribute><attribute><name>Median Condo Value</name><values><neighborhood><value type="USD">249600</value></neighborhood><city><value type="USD">209500</value></city><nation><value type="USD">186100</value></nation></values></attribute><attribute><name>Median 2-Bedroom Home Value</name><values><city><value type="USD">266100</value></city><nation><value type="USD">139500</value></nation></values></attribute><attribute><name>Median 3-Bedroom Home Value</name><values><city><value type="USD">283300</value></city><nation><value type="USD">173800</value></nation></values></attribute><attribute><name>Median 4-Bedroom Home Value</name><values><city><value type="USD">277100</value></city><nation><value type="USD">292500</value></nation></values></attribute><attribute><name>Percent Homes Decreasing</name><values><neighborhood><value type="percent">0.873</value></neighborhood><city><value type="percent">0.382</value></city><nation><value type="percent">0.321</value></nation></values></attribute><attribute><name>Percent Listing Price Reduction</name><values><neighborhood><value>0</value></neighborhood><city><value>0</value></city><nation><value>0</value></nation></values></attribute><attribute><name>Median List Price Per Sq Ft</name><values><neighborhood><value type="USD">161</value></neighborhood><city><value type="USD">155</value></city><nation><value type="USD">115</value></nation></values></attribute><attribute><name>Median List Price</name><values><neighborhood><value>0</value></neighborhood><city><value>0</value></city><nation><value>0</value></nation></values></attribute><attribute><name>Median Sale Price</name><values><neighborhood><value>0</value></neighborhood><city><value type="USD">298100</value></city><nation><value type="USD">218900</value></nation></values></attribute><attribute><name>Homes For Sale</name><values><neighborhood><value>0</value></neighborhood><city><value>0</value></city><nation><value>0</value></nation></values></attribute><attribute><name>Homes Recently Sold</name><values><neighborhood><value>0</value></neighborhood><city><value>0</value></city><nation><value>0</value></nation></values></attribute><attribute><name>Property Tax</name><values><neighborhood><value type="USD">3607</value></neighborhood><city><value type="USD">2372</value></city><nation><value type="USD">2116</value></nation></values></attribute><attribute><name>Turnover (Sold Within Last Yr.)</name><values><neighborhood><value type="percent">0.091</value></neighborhood><city><value type="percent">0.052</value></city><nation><value type="percent">0.04</value></nation></values></attribute><attribute><name>Median Value Per Sq Ft</name><values><neighborhood><value>0</value></neighborhood><city><value>0</value></city><nation><value>0</value></nation></values></attribute><attribute><name>1-Yr. Change</name><values><neighborhood><value type="percent">0.156</value></neighborhood><city><value type="percent">0.046</value></city><nation><value type="percent">0.033</value></nation></values></attribute><attribute><name>Homes For Sale By Owner</name><values><neighborhood><value /></neighborhood><city><value /></city><nation><value /></nation></values></attribute><attribute><name>New Construction</name><values><neighborhood><value /></neighborhood><city><value /></city><nation><value /></nation></values></attribute><attribute><name>Foreclosures</name><values><neighborhood><value /></neighborhood><city><value /></city><nation><value /></nation></values></attribute></data></table></tables></page><page><name>Homes &amp; Real Estate</name><tables><table><name>Homes &amp; Real Estate Data</name><data><attribute><name>Owners</name><values><neighborhood><value type="percent">0.17477351</value></neighborhood><city><value type="percent">0.43780281</value></city><nation><value type="percent">0.66268764</value></nation></values></attribute><attribute><name>Renters</name><values><neighborhood><value type="percent">0.82522649</value></neighborhood><city><value type="percent">0.56219719</value></city><nation><value type="percent">0.33731236</value></nation></values></attribute><attribute><name>Median Home Size (Sq. Ft.)</name><values /></attribute><attribute><name>Avg. Year Built</name><values /></attribute><attribute><name>Single-Family Homes</name><values><city><value type="percent">0.3613336659269</value></city></values></attribute><attribute><name>Condos</name><values><city><value type="percent">0.3811535742396</value></city></values></attribute></data></table><table><name>Census Summary-Occupancy</name><data><attribute><name>Own</name><value type="percent">0.17477351</value></attribute><attribute><name>Rent</name><value type="percent">0.82522649</value></attribute></data></table></tables></page><page><name>People</name><tables><table><name>People Data</name><data><attribute><name>Median Household Income</name><values><neighborhood><value currency="USD">10513.5006579525</value></neighborhood><city><value currency="USD">38625</value></city><nation><value currency="USD">44512.0130806292</value></nation></values></attribute><attribute><name>Single Males</name><values><neighborhood><value type="percent">0.208321330703834</value></neighborhood><city><value type="percent">0.210184780949744</value></city><nation><value type="percent">0.146462187349365</value></nation></values></attribute><attribute><name>Single Females</name><values><neighborhood><value type="percent">0.315288764800165</value></neighborhood><city><value type="percent">0.198669690742141</value></city><nation><value type="percent">0.124578258618535</value></nation></values></attribute><attribute><name>Median Age</name><values><neighborhood><value>34</value></neighborhood><city><value>33</value></city><nation><value>36</value></nation></values></attribute><attribute><name>Homes With Kids</name><values><neighborhood><value type="percent">0.220054739985071</value></neighborhood><city><value type="percent">0.285350539189652</value></city><nation><value type="percent">0.313623902816284</value></nation></values></attribute><attribute><name>Average Household Size</name><values><neighborhood><value>2.19084174050355</value></neighborhood><city><value>2.67</value></city><nation><value>2.58883240001203</value></nation></values></attribute><attribute><name>Average Commute Time (Minutes)</name><values><neighborhood><value>34.761903608035105</value></neighborhood><city><value>35.44053647246415</value></city><nation><value>26.375545725891282</value></nation></values></attribute></data></table><table><name>Census Summary-AgeDecade</name><data><attribute><name>&gt;=70s</name><value type="percent">0.103657120100886</value></attribute><attribute><name>0s</name><value type="percent">0.199222336530271</value></attribute><attribute><name>10s</name><value type="percent">0.133574486443434</value></attribute><attribute><name>20s</name><value type="percent">0.10258409938163</value></attribute><attribute><name>30s</name><value type="percent">0.167147866679941</value></attribute><attribute><name>40s</name><value type="percent">0.138668569342581</value></attribute><attribute><name>50s</name><value type="percent">0.0969700992267614</value></attribute><attribute><name>60s</name><value type="percent">0.0581754222944944</value></attribute></data></table><table><name>Census Summary-CommuteTime</name><data><attribute><name>&lt;10min</name><value type="percent">0</value></attribute><attribute><name>&gt;=60min</name><value type="percent">0.193389711405656</value></attribute><attribute><name>10-20min</name><value type="percent">0.29055707674041</value></attribute><attribute><name>20-30min</name><value type="percent">0.238556785965252</value></attribute><attribute><name>30-45min</name><value type="percent">0.150500375584579</value></attribute><attribute><name>45-60min</name><value type="percent">0.126996050304102</value></attribute></data></table><table><name>Census Summary-Household</name><data><attribute><name>NoKids</name><value type="percent">0.779945260014929</value></attribute><attribute><name>WithKids</name><value type="percent">0.220054739985071</value></attribute></data></table><table><name>Census Summary-RelationshipStatus</name><data><attribute><name>Divorced-Female</name><value type="percent">0.0726362206120233</value></attribute><attribute><name>Divorced-Male</name><value type="percent">0.0346340490593632</value></attribute><attribute><name>Married-Female</name><value type="percent">0.0969812463530472</value></attribute><attribute><name>Married-Male</name><value type="percent">0.144954833181916</value></attribute><attribute><name>Single-Female</name><value type="percent">0.315288764800165</value></attribute><attribute><name>Single-Male</name><value type="percent">0.208321330703834</value></attribute><attribute><name>Widowed-Female</name><value type="percent">0.0917296343075775</value></attribute><attribute><name>Widowed-Male</name><value type="percent">0.0354539209820736</value></attribute></data></table></tables><segmentation><liveshere><title>Ramen Metros</title><name>Lower-income urban singles.</name><description>Most rent their apartment or condo. Some have a college education and work in services and the professional sector.</description></liveshere><liveshere><title>Urban Bootstrappers</title><name>Lower-scale single parents living in the city.</name><description>Single parents who support themselves and their children on a low income. A high proportion are female. Most have a high school education or lower, and most rent their homes.</description></liveshere><liveshere><title>Elder Renters</title><name>Urban senior renters.</name><description>Retirement-age seniors who live in the city and rent. Low income. Most have a high school education or lower.</description></liveshere></segmentation><uniqueness><category type="Education"><characteristic>Did not complete high school</characteristic></category><category type="Employment"><characteristic>Self-employed (unincorporated businesses)</characteristic><characteristic>Work for non-profits</characteristic><characteristic>Work for the government</characteristic><characteristic>Work in architecture or engineering</characteristic><characteristic>Work in business and financial occupations</characteristic><characteristic>Work in community or social services occupations</characteristic><characteristic>Work in computer or mathematical occupations</characteristic><characteristic>Work in education, training, or library occupations</characteristic><characteristic>Work in installation, maintenance, or repair occupations</characteristic><characteristic>Work in legal occupations</characteristic><characteristic>Work in management-level occupations</characteristic><characteristic>Work in office and administrative support occupations</characteristic></category><category type="People &amp; Culture"><characteristic>Born in the South</characteristic><characteristic>Divorced females</characteristic><characteristic>Separated males</characteristic><characteristic>Single females</characteristic><characteristic>Single males</characteristic><characteristic>Widowed females</characteristic><characteristic>Widowed males</characteristic></category><category type="Transportation"><characteristic>Get to work by bus</characteristic><characteristic>Get to work by subway</characteristic><characteristic>Get to work by train</characteristic><characteristic>Work at home</characteristic></category></uniqueness></page></pages></response></ns0:demographics>